requestsloginsession/__init__.py
requestsloginsession/requestsloginsession.py
requestsloginsession-0.7.1.dist-info/LICENSE.txt
requestsloginsession-0.7.1.dist-info/METADATA
requestsloginsession-0.7.1.dist-info/WHEEL
requestsloginsession-0.7.1.dist-info/top_level.txt
requestsloginsession-0.7.1.dist-info/RECORD
