Metadata-Version: 2.1
Name: requestsloginsession
Version: 0.7.1
Summary: Wrapper for requests that saves cookie data between script runs, typically for login sessions
Home-page: https://github.com/damonjavert/requestsloginsession
Author: DamonJavert
Author-email: damonjavert@protonmail.com
License: GPLv3
Project-URL: Bug Tracker, https://github.com/damonjavert/requestsloginsession/issues
Project-URL: repository, https://github.com/damonjavert/requestsloginsession
Platform: unix
Platform: linux
Platform: osx
Platform: cygwin
Platform: win32
Classifier: Programming Language :: Python :: 3
Classifier: Programming Language :: Python :: 3 :: Only
Classifier: Programming Language :: Python :: 3.8
Classifier: Programming Language :: Python :: 3.9
Classifier: Programming Language :: Python :: 3.10
Classifier: Programming Language :: Python :: 3.11
Classifier: Programming Language :: Python :: 3.12
Classifier: Development Status :: 5 - Production/Stable
Classifier: License :: OSI Approved :: GNU General Public License v3 (GPLv3)
Classifier: Operating System :: OS Independent
Requires-Python: >=3.8
License-File: LICENSE.txt
Requires-Dist: requests (>=2)
Requires-Dist: urllib3 (>=1.25)
Requires-Dist: pathlib (>=1.0)
